restDbApi/__init__.py
restDbApi/db_engine_specs.py
restDbApi/rest_api_adapter.py
restDbApi/rest_api_dialect.py
restDbApi/utils.py
rest_db_api-1.1.0.dist-info/LICENSE
rest_db_api-1.1.0.dist-info/METADATA
rest_db_api-1.1.0.dist-info/WHEEL
rest_db_api-1.1.0.dist-info/entry_points.txt
rest_db_api-1.1.0.dist-info/top_level.txt
rest_db_api-1.1.0.dist-info/RECORD
