Metadata-Version: 2.1
Name: rest-db-api
Version: 1.1.0
Summary: A rest db api designed to be integrated with apache superset
Author-email: Satvik Nema <saviknema@gmail.com>
License: MIT License
Project-URL: Homepage, https://github.com/SatvikNema/rest-db-api
Project-URL: Bug Tracker, https://github.com/SatvikNema/rest-db-api/issues
Keywords: rest,dbapi,sqlalchemy,adapter,superset
Classifier: Programming Language :: Python :: 3
Classifier: License :: OSI Approved :: MIT License
Classifier: Operating System :: OS Independent
Requires-Python: >=3.7
License-File: LICENSE
Requires-Dist: SQLAlchemy (<=1.4.39)
Requires-Dist: shillelagh
Requires-Dist: requests-cache
Requires-Dist: jsonpath-python
